README.md
setup.py
jandan_cli/__init__.py
jandan_cli/cli.py
jandan_cli/const.py
jandan_cli/crawler.py
jandan_cli/exceptions.py
jandan_cli/logs.py
jandan_cli.egg-info/PKG-INFO
jandan_cli.egg-info/SOURCES.txt
jandan_cli.egg-info/dependency_links.txt
jandan_cli.egg-info/entry_points.txt
jandan_cli.egg-info/not-zip-safe
jandan_cli.egg-info/requires.txt
jandan_cli.egg-info/top_level.txt
jandan_cli/utils/__init__.py
jandan_cli/utils/func.py
jandan_cli/utils/output.py