Metadata-Version: 1.2
Name: jandan-cli
Version: 0.0.2
Summary: jandan cli
Home-page: https://github.com/lonycc/jandan-py
Author: lonycc
Author-email: xcc@163.com
License: MIT
Platform: any
Classifier: Environment :: Web Environment
Classifier: Intended Audience :: Developers
Classifier: License :: OSI Approved :: MIT License
Classifier: Operating System :: OS Independent
Classifier: Programming Language :: Python
Classifier: Programming Language :: Python :: 3.5
Classifier: Programming Language :: Python :: 3.6
Classifier: Programming Language :: Python :: 3.7
Classifier: Topic :: Terminals
Requires-Python: >=3
